snake_env/__init__.py
snake_env/snake_big.py
snake_env/snake_small.py
snake_env-1.2.dist-info/METADATA
snake_env-1.2.dist-info/WHEEL
snake_env-1.2.dist-info/licenses/LICENSE
snake_env-1.2.dist-info/RECORD
