Metadata-Version: 2.1
Name: snake_env
Version: 1.2
Summary: A gymnasium environment for the Snake game
Author: Maksymilian Piotrowski
License-File: LICENSE
Classifier: License :: OSI Approved :: MIT License
Classifier: Operating System :: OS Independent
Classifier: Programming Language :: Python :: 3
Requires-Python: >=3.7
